selenium_screenshots/__init__.py
selenium_screenshots/additional.py
selenium_screenshots/class_screenshots.py
selenium_screenshots/exceptions.py
selenium_screenshots/func_screenshot.py
selenium_screenshots-0.1.3.dist-info/LICENSE.txt
selenium_screenshots-0.1.3.dist-info/WHEEL
selenium_screenshots-0.1.3.dist-info/METADATA
selenium_screenshots-0.1.3.dist-info/RECORD
