Metadata-Version: 2.1
Name: selenium-screenshots
Version: 0.1.3
Summary: python package which helps to create many screenshots for selenium.webdriver
Home-page: https://github.com/stas-prokopiev/selenium_screenshots
License: MIT
Author: stanislav prokopyev
Requires-Python: >=3.7,<4.0
Classifier: License :: OSI Approved :: MIT License
Classifier: Programming Language :: Python :: 3
Classifier: Programming Language :: Python :: 3.10
Classifier: Programming Language :: Python :: 3.7
Classifier: Programming Language :: Python :: 3.8
Classifier: Programming Language :: Python :: 3.9
Requires-Dist: char (>=0.1.2,<0.2.0)
Requires-Dist: local-simple-database (>=0.1.10,<0.2.0)
Requires-Dist: tqdm (>=4.64.0,<5.0.0)
Project-URL: Repository, https://github.com/stas-prokopiev/selenium_screenshots
